{
  "minecraft:recipes/tools/fishing_rod": {
    "criteria": {
      "has_string": "2018-04-13 21:59:23 +0200"
    },
    "done": true
  },
  "minecraft:recipes/building_blocks/sandstone_slab": {
    "criteria": {
      "has_sandstone": "2018-04-13 21:44:28 +0200"
    },
    "done": true
  },
  "minecraft:recipes/combat/bow": {
    "criteria": {
      "has_string": "2018-04-13 21:59:23 +0200"
    },
    "done": true
  },
  "minecraft:recipes/redstone/tnt": {
    "criteria": {
      "has_gunpowder": "2018-04-13 21:59:19 +0200"
    },
    "done": true
  },
  "minecraft:recipes/building_blocks/string_to_wool": {
    "criteria": {
      "has_string": "2018-04-13 21:59:23 +0200"
    },
    "done": true
  },
  "minecraft:recipes/redstone/dispenser": {
    "criteria": {
      "has_bow": "2018-04-13 22:46:03 +0200"
    },
    "done": true
  },
  "minecraft:recipes/transportation/dark_oak_boat": {
    "criteria": {
      "entered_water": "2018-04-13 22:08:27 +0200"
    },
    "done": true
  },
  "minecraft:recipes/redstone/repeater": {
    "criteria": {
      "has_redstone_torch": "2018-04-13 22:55:14 +0200"
    },
    "done": true
  },
  "minecraft:recipes/building_blocks/mossy_cobblestone": {
    "criteria": {
      "has_vine": "2018-04-13 22:45:24 +0200"
    },
    "done": true
  },
  "minecraft:recipes/building_blocks/sandstone_stairs": {
    "criteria": {
      "has_sandstone": "2018-04-13 21:44:28 +0200"
    },
    "done": true
  },
  "minecraft:recipes/building_blocks/stonebrick": {
    "criteria": {
      "has_stone": "2018-04-13 21:40:33 +0200"
    },
    "done": true
  },
  "minecraft:recipes/building_blocks/red_sandstone_stairs": {
    "criteria": {
      "has_red_sandstone": "2018-04-13 21:44:31 +0200"
    },
    "done": true
  },
  "minecraft:recipes/redstone/tripwire_hook": {
    "criteria": {
      "has_string": "2018-04-13 21:59:23 +0200"
    },
    "done": true
  },
  "minecraft:recipes/building_blocks/red_sandstone_slab": {
    "criteria": {
      "has_red_sandstone": "2018-04-13 21:44:31 +0200"
    },
    "done": true
  },
  "minecraft:recipes/redstone/trapped_chest": {
    "criteria": {
      "has_tripwire_hook": "2018-04-13 22:50:45 +0200"
    },
    "done": true
  },
  "minecraft:recipes/brewing/cauldron": {
    "criteria": {
      "has_water_bucket": "2018-04-13 22:08:21 +0200"
    },
    "done": true
  },
  "minecraft:recipes/building_blocks/chiseled_red_sandstone": {
    "criteria": {
      "has_red_sandstone": "2018-04-13 21:44:31 +0200"
    },
    "done": true
  },
  "minecraft:adventure/adventuring_time": {
    "criteria": {
      "swampland": "2018-04-13 21:53:06 +0200",
      "taiga": "2018-04-13 21:54:52 +0200"
    },
    "done": false
  },
  "minecraft:recipes/redstone/redstone": {
    "criteria": {
      "has_redstone_block": "2018-04-13 21:42:41 +0200"
    },
    "done": true
  },
  "minecraft:recipes/misc/bone_meal_from_bone": {
    "criteria": {
      "has_bone": "2018-04-13 21:56:52 +0200"
    },
    "done": true
  },
  "minecraft:recipes/building_blocks/stone_brick_slab": {
    "criteria": {
      "has_stonebrick": "2018-04-13 22:20:37 +0200"
    },
    "done": true
  },
  "minecraft:recipes/decorations/chest": {
    "criteria": {
      "has_lots_of_items": "2018-04-13 21:59:23 +0200"
    },
    "done": true
  },
  "minecraft:recipes/misc/diamond": {
    "criteria": {
      "has_diamond_block": "2018-04-13 22:56:19 +0200"
    },
    "done": true
  },
  "minecraft:recipes/transportation/birch_boat": {
    "criteria": {
      "entered_water": "2018-04-13 22:08:27 +0200"
    },
    "done": true
  },
  "minecraft:story/shiny_gear": {
    "criteria": {
      "diamond_helmet": "2018-04-13 22:57:56 +0200"
    },
    "done": true
  },
  "minecraft:recipes/redstone/stone_button": {
    "criteria": {
      "has_stone": "2018-04-13 21:40:33 +0200"
    },
    "done": true
  },
  "minecraft:recipes/transportation/acacia_boat": {
    "criteria": {
      "entered_water": "2018-04-13 22:08:27 +0200"
    },
    "done": true
  },
  "minecraft:recipes/building_blocks/stone_slab": {
    "criteria": {
      "has_stone": "2018-04-13 21:40:33 +0200"
    },
    "done": true
  },
  "minecraft:recipes/redstone/stone_pressure_plate": {
    "criteria": {
      "has_stone": "2018-04-13 21:40:33 +0200"
    },
    "done": true
  },
  "minecraft:recipes/transportation/boat": {
    "criteria": {
      "entered_water": "2018-04-13 22:08:27 +0200"
    },
    "done": true
  },
  "minecraft:recipes/transportation/jungle_boat": {
    "criteria": {
      "entered_water": "2018-04-13 22:08:27 +0200"
    },
    "done": true
  },
  "minecraft:recipes/building_blocks/chiseled_stonebrick": {
    "criteria": {
      "has_stonebrick": "2018-04-13 22:20:37 +0200"
    },
    "done": true
  },
  "minecraft:recipes/misc/gold_ingot_from_block": {
    "criteria": {
      "has_gold_block": "2018-04-13 22:55:44 +0200"
    },
    "done": true
  },
  "minecraft:recipes/transportation/spruce_boat": {
    "criteria": {
      "entered_water": "2018-04-13 22:08:27 +0200"
    },
    "done": true
  },
  "minecraft:recipes/building_blocks/stone_brick_stairs": {
    "criteria": {
      "has_stonebrick": "2018-04-13 22:20:37 +0200"
    },
    "done": true
  }
}